pgfuzzy
